{
  "attachment": {
    "accessible": false,
    "alternative_format_contact_email": "alternativeformats@homeoffice.gov.uk",
    "attachment_type": "file",
    "command_paper_number": "",
    "content_type": "text/csv",
    "file_size": 9505118,
    "filename": "2024-04-18_-_Worker_and_Temporary_Worker.csv",
    "hoc_paper_number": "",
    "id": "7947273",
    "isbn": "",
    "preview_url": "https://assets.publishing.service.gov.uk/media/1236017/2024-04-18_-_Worker_and_Temporary_Worker.csv/preview",
    "title": "Register of Worker and Temporary Worker licensed sponsors",
    "unique_reference": "",
    "unnumbered_command_paper": false,
    "unnumbered_hoc_paper": false,
    "url": "https://assets.publishing.service.gov.uk/media/6620eeab77a30aa0c4757daf/2024-04-18_-_Worker_and_Temporary_Worker.csv"
  },
  "change_history": {
    "note": "Updated register of licensed sponsors.",
    "public_timestamp": "2024-04-18T12:16:34.000+01:00"
  }
}
